xy_web_work/ModuleData.py
xy_web_work/WebWork.py
xy_web_work/Work.py
xy_web_work/__init__.py
xy_web_work/Admin/Admin.py
xy_web_work/Admin/__init__.py
xy_web_work/Backup/Backup.py
xy_web_work/Backup/__init__.py
xy_web_work/Build/Build.py
xy_web_work/Build/Way.py
xy_web_work/Build/__init__.py
xy_web_work/Build/Connector/__init__.py
xy_web_work/Build/Connector/CPython/CPython.py
xy_web_work/Build/Connector/CPython/__init__.py
xy_web_work/Build/Connector/IPython/IPython.py
xy_web_work/Build/Connector/IPython/__init__.py
xy_web_work/Build/Connector/IronPython/IronPython.py
xy_web_work/Build/Connector/IronPython/__init__.py
xy_web_work/Build/Connector/JPython/JPython.py
xy_web_work/Build/Connector/JPython/__init__.py
xy_web_work/Build/Connector/PyPy/PyPy.py
xy_web_work/Build/Connector/PyPy/__init__.py
xy_web_work/Build/Library/__init__.py
xy_web_work/Build/Library/Dynamic/Dynamic.py
xy_web_work/Build/Library/Dynamic/__init__.py
xy_web_work/Build/Library/Static/Static.py
xy_web_work/Build/Library/Static/__init__.py
xy_web_work/Database/Database.py
xy_web_work/Database/Way.py
xy_web_work/Database/__init__.py
xy_web_work/Database/Connector/__init__.py
xy_web_work/Database/Connector/Mongo/Mongo.py
xy_web_work/Database/Connector/Mongo/__init__.py
xy_web_work/Database/Connector/Mysql/Backup.py
xy_web_work/Database/Connector/Mysql/Log.py
xy_web_work/Database/Connector/Mysql/Mysql.py
xy_web_work/Database/Connector/Mysql/__init__.py
xy_web_work/Database/Connector/PostgreSQL/Backup.py
xy_web_work/Database/Connector/PostgreSQL/Log.py
xy_web_work/Database/Connector/PostgreSQL/PostgreSQL.py
xy_web_work/Database/Connector/PostgreSQL/__init__.py
xy_web_work/Database/Connector/Redis/Backup.py
xy_web_work/Database/Connector/Redis/Log.py
xy_web_work/Database/Connector/Redis/Redis.py
xy_web_work/Database/Connector/Redis/__init__.py
xy_web_work/Database/Connector/Sqlite/Backup.py
xy_web_work/Database/Connector/Sqlite/Log.py
xy_web_work/Database/Connector/Sqlite/Sqlite.py
xy_web_work-1.0.7.dist-info/LICENSE
xy_web_work-1.0.7.dist-info/METADATA
xy_web_work-1.0.7.dist-info/WHEEL
xy_web_work-1.0.7.dist-info/top_level.txt
xy_web_work-1.0.7.dist-info/RECORD
