Metadata-Version: 2.1
Name: xy_web_work
Version: 1.0.7
Summary: xy_web_service web工作模块
Author-email: 余洋 <yuyangit.0515@qq.com>
Classifier: Programming Language :: Python :: 3
Requires-Python: >=3.11.3
License-File: LICENSE
Requires-Dist: importlib-resources
Requires-Dist: xy-singleton
Requires-Dist: xy-file
Requires-Dist: xy-configure
Requires-Dist: xy-settings
Requires-Dist: xy-work
Requires-Dist: xy-web-settings
